setup.py
test_pro/__init__.py
test_pro/pro.py
test_pro.egg-info/PKG-INFO
test_pro.egg-info/SOURCES.txt
test_pro.egg-info/dependency_links.txt
test_pro.egg-info/top_level.txt