Metadata-Version: 1.0
Name: test-pro
Version: 1.0.0
Summary: Quantitative trading 
Home-page: https://upload.pypi.org/legacy/
Author: zhoujin
Author-email: zhoujin9611@163.com
License: UNKNOWN
Platform: any
